Metadata-Version: 2.1
Name: salaryyy
Version: 1.0.0
Summary: tax payment
Author: Kevi Shtrepi
Author-email: <mail@gmail.com>
Keywords: fraplustree,SDA,fra,tree
Classifier: Development Status :: 1 - Planning
Classifier: Intended Audience :: Developers
Classifier: Programming Language :: Python :: 3
Classifier: Operating System :: Unix
Classifier: Operating System :: MacOS :: MacOS X
Classifier: Operating System :: Microsoft :: Windows
